constance/utils.py
constance/__init__.py
constance/base.py
constance/context_processors.py
constance/admin.py
constance/apps.py
constance/models.py
constance/settings.py
constance/templates/admin/constance/change_list.html
constance/locale/ru/LC_MESSAGES/django.mo
constance/locale/ru/LC_MESSAGES/django.po
constance/locale/cs_CZ/LC_MESSAGES/django.mo
constance/locale/cs_CZ/LC_MESSAGES/django.po
constance/locale/en/LC_MESSAGES/django.mo
constance/locale/en/LC_MESSAGES/django.po
constance/locale/pl/LC_MESSAGES/django.mo
constance/locale/pl/LC_MESSAGES/django.po
constance/locale/de/LC_MESSAGES/django.mo
constance/locale/de/LC_MESSAGES/django.po
constance/locale/zh_CN/LC_MESSAGES/django.mo
constance/locale/zh_CN/LC_MESSAGES/django.po
constance/locale/it/LC_MESSAGES/django.mo
constance/locale/it/LC_MESSAGES/django.po
constance/locale/es/LC_MESSAGES/django.mo
constance/locale/es/LC_MESSAGES/django.po
constance/backends/__init__.py
constance/backends/redisd.py
constance/backends/database/__init__.py
constance/backends/database/models.py
constance/backends/database/migrations/__init__.py
constance/backends/database/migrations/0001_initial.py
constance/backends/database/south_migrations/__init__.py
constance/backends/database/south_migrations/0002_auto__chg_field_constance_key__add_unique_constance_key.py
constance/backends/database/south_migrations/0001_initial.py
django_constance_updated-1.0.1.dist-info/RECORD
django_constance_updated-1.0.1.dist-info/top_level.txt
django_constance_updated-1.0.1.dist-info/metadata.json
django_constance_updated-1.0.1.dist-info/DESCRIPTION.rst
django_constance_updated-1.0.1.dist-info/WHEEL
django_constance_updated-1.0.1.dist-info/METADATA
