Metadata-Version: 2.0
Name: django-constance-updated
Version: 1.0.1
Summary: Django live settings with pluggable backends, including Redis.
Home-page: http://github.com/jezdez/django-constance
Author: Jannis Leidel
Author-email: jannis@leidel.info
License: BSD
Keywords: django,libraries,settings,redis
Platform: any
Classifier: Development Status :: 5 - Production/Stable
Classifier: Environment :: Web Environment
Classifier: Framework :: Django
Classifier: Intended Audience :: Developers
Classifier: Natural Language :: English
Classifier: License :: OSI Approved :: BSD License
Classifier: Operating System :: OS Independent
Classifier: Programming Language :: Python
Classifier: Programming Language :: Python :: 2
Classifier: Programming Language :: Python :: 2.6
Classifier: Programming Language :: Python :: 2.7
Classifier: Programming Language :: Python :: 3
Classifier: Programming Language :: Python :: 3.2
Classifier: Programming Language :: Python :: 3.3
Classifier: Programming Language :: Python :: 3.4
Classifier: Topic :: Utilities
Provides-Extra: database
Requires-Dist: django-picklefield; extra == 'database'
Provides-Extra: redis
Requires-Dist: redis; extra == 'redis'
